{
  "entries": {
    "tap": {
      "dteoh/sqa": {
        "revision": "fa22311a66a9bdaf3c40eb12dfd0bc91e55de0a8"
      },
      "homebrew/bundle": {
        "revision": "78513292658ff002a6a816bdeb9d286150ee1a16"
      },
      "homebrew/cask": {
        "revision": "a6bf302b9a143d131159bfe223a33d7e01cabf7e"
      },
      "homebrew/cask-drivers": {
        "revision": "df0d300c92dcaefc31d0b784b92484ab6451b77b"
      },
      "homebrew/cask-versions": {
        "revision": "bc6927a04eccd3f91b206b6161138549279c0184"
      },
      "homebrew/core": {
        "revision": "a5a91200d6813d2c14e6787b70707571e82485c8"
      },
      "homebrew/services": {
        "revision": "0448884d8213af19280ee8fab30af89cca20f630"
      },
      "github/gh": {
        "revision": "209f59cda890de69b74c224982591642c21323d3"
      },
      "homebrew/cask-fonts": {
        "revision": "feaeb0e4619eb4935438d0bb10fbcbac2552372b"
      },
      "acourtneybrown/fonts": {
        "revision": "9e355fd28c87b63cb4d2300af8367b9757a537d3"
      }
    },
    "brew": {
      "openssl": null,
      "python": null,
      "asciinema": {
        "version": "2.0.2_3",
        "bottle": {
          "cellar": ":any_skip_relocation",
          "prefix": "/usr/local",
          "files": {
            "catalina": {
              "url": "https://homebrew.bintray.com/bottles/asciinema-2.0.2_3.catalina.bottle.tar.gz",
              "sha256": "caa76523c644cf5916cde300c407d89282509a0291cfa9c4812d888c26ce7f77"
            },
            "mojave": {
              "url": "https://homebrew.bintray.com/bottles/asciinema-2.0.2_3.mojave.bottle.tar.gz",
              "sha256": "b1a1aff9cf3f46328f0df80773a85898db70453fff4785e26e7ee4d6f12ef408"
            },
            "high_sierra": {
              "url": "https://homebrew.bintray.com/bottles/asciinema-2.0.2_3.high_sierra.bottle.tar.gz",
              "sha256": "4ce78d8edeeb635ad7cf2f5edd88770baaa72d623ecc471fb0e8f5e12efb0e04"
            }
          }
        }
      },
      "augeas": {
        "version": "1.12.0",
        "bottle": {
          "cellar": "/usr/local/Cellar",
          "prefix": "/usr/local",
          "files": {
            "catalina": {
              "url": "https://homebrew.bintray.com/bottles/augeas-1.12.0.catalina.bottle.tar.gz",
              "sha256": "00a45b8b446df0a95c2c45cbe608410df2d7be7787247f4b3a8fc1c2c19b41b6"
            },
            "mojave": {
              "url": "https://homebrew.bintray.com/bottles/augeas-1.12.0.mojave.bottle.tar.gz",
              "sha256": "9a561491e3574dfe2cfe7da2a618c12d02218f88f760de46722d9b603e4f27ba"
            },
            "high_sierra": {
              "url": "https://homebrew.bintray.com/bottles/augeas-1.12.0.high_sierra.bottle.tar.gz",
              "sha256": "0e1477f692cf67442dfcaf7c20a24733838df072ec867f59322070a7eaf3f925"
            },
            "sierra": {
              "url": "https://homebrew.bintray.com/bottles/augeas-1.12.0.sierra.bottle.tar.gz",
              "sha256": "55b3fab93f2ec4a703dc2bb3b3d58c47375456bdb5f0308e0856b231d309c02d"
            }
          }
        }
      },
      "awscli": {
        "version": "2.0.57",
        "bottle": {
          "cellar": "/usr/local/Cellar",
          "prefix": "/usr/local",
          "files": {
            "catalina": {
              "url": "https://homebrew.bintray.com/bottles/awscli-2.0.57.catalina.bottle.tar.gz",
              "sha256": "a7f2553bf36b3138af2ea3861baa22224fbfbb88481182488e9cb23693dd5454"
            },
            "mojave": {
              "url": "https://homebrew.bintray.com/bottles/awscli-2.0.57.mojave.bottle.tar.gz",
              "sha256": "ed83511bfb9f9e85ab295b501ea93bfbc78f238f7bb4ef3cfb6b37c4559590eb"
            },
            "high_sierra": {
              "url": "https://homebrew.bintray.com/bottles/awscli-2.0.57.high_sierra.bottle.tar.gz",
              "sha256": "7be7a6cb59321f8ddf875dfe4574d6517a62d4517d25092ca1364a1a01a10693"
            }
          }
        }
      },
      "azure-cli": {
        "version": "2.13.0",
        "bottle": {
          "cellar": ":any",
          "prefix": "/usr/local",
          "files": {
            "catalina": {
              "url": "https://homebrew.bintray.com/bottles/azure-cli-2.13.0.catalina.bottle.tar.gz",
              "sha256": "55aef02512835462cb02544e3c3a74cc26ca1b2fa0c4b039ba3ab5b1a2438b4f"
            },
            "mojave": {
              "url": "https://homebrew.bintray.com/bottles/azure-cli-2.13.0.mojave.bottle.tar.gz",
              "sha256": "4577ab4c6fa8009e69d2dabeaacb14c4827fe69bba8cefa51b5f4437ecd7b0fa"
            },
            "high_sierra": {
              "url": "https://homebrew.bintray.com/bottles/azure-cli-2.13.0.high_sierra.bottle.tar.gz",
              "sha256": "b221718a17349a0b31e26631cf899ff977640405e9073b46ff165e912438df67"
            }
          }
        }
      },
      "bash": {
        "version": "5.0.18",
        "bottle": {
          "cellar": "/usr/local/Cellar",
          "prefix": "/usr/local",
          "files": {
            "catalina": {
              "url": "https://homebrew.bintray.com/bottles/bash-5.0.18.catalina.bottle.tar.gz",
              "sha256": "c6e7b7a521a1cfb21f2872bde253bfd40150bd4ba36ada62c05fcdb73ae094c6"
            },
            "mojave": {
              "url": "https://homebrew.bintray.com/bottles/bash-5.0.18.mojave.bottle.tar.gz",
              "sha256": "ba0617f6d3f4e691f9863e2f73596da94671f4c0ca21a95b99f19eced315f2d4"
            },
            "high_sierra": {
              "url": "https://homebrew.bintray.com/bottles/bash-5.0.18.high_sierra.bottle.tar.gz",
              "sha256": "46023d0bafe68b838ada45ff6a66e63f7eac814eeb84e15a09d4b84a790ef49d"
            }
          }
        }
      },
      "bash-completion@2": {
        "version": "2.10_1",
        "bottle": {
          "cellar": ":any_skip_relocation",
          "prefix": "/usr/local",
          "files": {
            "catalina": {
              "url": "https://homebrew.bintray.com/bottles/bash-completion%402-2.10_1.catalina.bottle.tar.gz",
              "sha256": "b162bc315662861c84f428b262c9883d34ff7eab80ddff09148f81aef4d5d7ff"
            },
            "mojave": {
              "url": "https://homebrew.bintray.com/bottles/bash-completion%402-2.10_1.mojave.bottle.tar.gz",
              "sha256": "b162bc315662861c84f428b262c9883d34ff7eab80ddff09148f81aef4d5d7ff"
            },
            "high_sierra": {
              "url": "https://homebrew.bintray.com/bottles/bash-completion%402-2.10_1.high_sierra.bottle.tar.gz",
              "sha256": "b162bc315662861c84f428b262c9883d34ff7eab80ddff09148f81aef4d5d7ff"
            }
          }
        }
      },
      "bfg": {
        "version": "1.13.0_1",
        "bottle": false
      },
      "cmake": {
        "version": "3.18.4",
        "bottle": {
          "cellar": ":any_skip_relocation",
          "prefix": "/usr/local",
          "files": {
            "catalina": {
              "url": "https://homebrew.bintray.com/bottles/cmake-3.18.4.catalina.bottle.tar.gz",
              "sha256": "c7c42e66c63448e4aee44498b374c9985f477b129fccca5dd9c13530d1e680ef"
            },
            "mojave": {
              "url": "https://homebrew.bintray.com/bottles/cmake-3.18.4.mojave.bottle.tar.gz",
              "sha256": "a0b167ad7f2fbf6f6dbcca9d74cb09acbd7822c54873803e940abf04272f8028"
            },
            "high_sierra": {
              "url": "https://homebrew.bintray.com/bottles/cmake-3.18.4.high_sierra.bottle.tar.gz",
              "sha256": "98704ab50ed76df9214083c01e373277ba02aad43c858182be7ed1466d005326"
            }
          }
        }
      },
      "coreutils": {
        "version": "8.32",
        "bottle": {
          "cellar": "/usr/local/Cellar",
          "prefix": "/usr/local",
          "files": {
            "catalina": {
              "url": "https://homebrew.bintray.com/bottles/coreutils-8.32.catalina.bottle.1.tar.gz",
              "sha256": "f40ba727ec1bb54300c7c79804f410a62341b63f3fba41d78ef34e5d369fe9fc"
            },
            "mojave": {
              "url": "https://homebrew.bintray.com/bottles/coreutils-8.32.mojave.bottle.1.tar.gz",
              "sha256": "91cd269ea5eff54a3074e0c3cd0995911c5989a4eb87a3c27b17a765c48f494e"
            },
            "high_sierra": {
              "url": "https://homebrew.bintray.com/bottles/coreutils-8.32.high_sierra.bottle.1.tar.gz",
              "sha256": "25c71d9d9a156cc8dfaa52b35dad1f9d49df55e97748fb5ab9522f65aeed4dca"
            }
          }
        }
      },
      "dark-mode": {
        "version": "3.0.1",
        "bottle": {
          "cellar": ":any_skip_relocation",
          "prefix": "/usr/local",
          "files": {
            "catalina": {
              "url": "https://homebrew.bintray.com/bottles/dark-mode-3.0.1.catalina.bottle.tar.gz",
              "sha256": "b9ce8876210cccd70e87ed5781a313f4b2705330453cd4af7ff2474f659d184e"
            },
            "mojave": {
              "url": "https://homebrew.bintray.com/bottles/dark-mode-3.0.1.mojave.bottle.tar.gz",
              "sha256": "bfb3cbcc43a333d6ca8ef8c52c89dc6d0cc23938f4e4fbd6ac13683e4ad63bd6"
            }
          }
        }
      },
      "dpkg": {
        "version": "1.20.0",
        "bottle": {
          "cellar": "/usr/local/Cellar",
          "prefix": "/usr/local",
          "files": {
            "catalina": {
              "url": "https://homebrew.bintray.com/bottles/dpkg-1.20.0.catalina.bottle.tar.gz",
              "sha256": "41dcad707b4741c74282184d8eda0e2d02121dd5cb52ad4ef816bfb842725994"
            },
            "mojave": {
              "url": "https://homebrew.bintray.com/bottles/dpkg-1.20.0.mojave.bottle.tar.gz",
              "sha256": "f1c7f9c37c420dee585d634fe0c29fb968d9d379a5be4f56d94a48b51666bcd4"
            },
            "high_sierra": {
              "url": "https://homebrew.bintray.com/bottles/dpkg-1.20.0.high_sierra.bottle.tar.gz",
              "sha256": "de1c3a3f1f2042699e6df4e9a793fb1e0fff1d194e2eff56c37d9cf4d24ab025"
            }
          }
        }
      },
      "ffmpeg": {
        "version": "4.3.1_1",
        "bottle": {
          "cellar": "/usr/local/Cellar",
          "prefix": "/usr/local",
          "files": {
            "catalina": {
              "url": "https://homebrew.bintray.com/bottles/ffmpeg-4.3.1_1.catalina.bottle.1.tar.gz",
              "sha256": "1924b8c971e7c2b2fd4a49ffdd2825df5048f5047b18a6454d0df6107e49d9a8"
            },
            "mojave": {
              "url": "https://homebrew.bintray.com/bottles/ffmpeg-4.3.1_1.mojave.bottle.1.tar.gz",
              "sha256": "e67748ccac6f4920ea740e526c34ce0a6c1087b645d41abbeed2c8e570c9a636"
            },
            "high_sierra": {
              "url": "https://homebrew.bintray.com/bottles/ffmpeg-4.3.1_1.high_sierra.bottle.1.tar.gz",
              "sha256": "5c2967fa5562347cabe3678a809463b28636f544f975bd4545720aca66de90c3"
            }
          }
        }
      },
      "findutils": {
        "version": "4.7.0",
        "bottle": {
          "cellar": ":any_skip_relocation",
          "prefix": "/usr/local",
          "files": {
            "catalina": {
              "url": "https://homebrew.bintray.com/bottles/findutils-4.7.0.catalina.bottle.tar.gz",
              "sha256": "f9ba06f4d48275e8cab659450b05e77873e909f31104df450201a83d465ed1ca"
            },
            "mojave": {
              "url": "https://homebrew.bintray.com/bottles/findutils-4.7.0.mojave.bottle.tar.gz",
              "sha256": "3c609b729a1dc859459282a856ff6c164cd8388e531dad4e58c8d4c7acb670fb"
            },
            "high_sierra": {
              "url": "https://homebrew.bintray.com/bottles/findutils-4.7.0.high_sierra.bottle.tar.gz",
              "sha256": "996a9fe2b1829fdf7b7257bead0ef0c4315832e9ba21b149779abeb59dcbde30"
            },
            "sierra": {
              "url": "https://homebrew.bintray.com/bottles/findutils-4.7.0.sierra.bottle.tar.gz",
              "sha256": "4b66ce398f2d5f5c65bf0b05fcc55334398e75cb965a17d781d7c3a15a4bba61"
            }
          }
        }
      },
      "gdub": {
        "version": "0.2.0",
        "bottle": false
      },
      "git": {
        "version": "2.28.0",
        "bottle": {
          "cellar": "/usr/local/Cellar",
          "prefix": "/usr/local",
          "files": {
            "catalina": {
              "url": "https://homebrew.bintray.com/bottles/git-2.28.0.catalina.bottle.tar.gz",
              "sha256": "6c4d10f29f78dcbefa12fab3e47e7755d5d2ca2e9bbc5aeee4838ad223296d0a"
            },
            "mojave": {
              "url": "https://homebrew.bintray.com/bottles/git-2.28.0.mojave.bottle.tar.gz",
              "sha256": "10f23bc63568fdeb598df2dd30fbb0ead31f2eef3c0990a8ac53f3e2005de82f"
            },
            "high_sierra": {
              "url": "https://homebrew.bintray.com/bottles/git-2.28.0.high_sierra.bottle.tar.gz",
              "sha256": "5095b064dfafb8cf4cabd017844f181d8eabaf45fb6965d2d30ed6de00c0e884"
            }
          }
        }
      },
      "git-lfs": {
        "version": "2.12.0",
        "bottle": {
          "cellar": ":any_skip_relocation",
          "prefix": "/usr/local",
          "files": {
            "catalina": {
              "url": "https://homebrew.bintray.com/bottles/git-lfs-2.12.0.catalina.bottle.tar.gz",
              "sha256": "1a6198c2a8cc656833215ee963e87536a3849405a560c9a52e50b578144d1142"
            },
            "mojave": {
              "url": "https://homebrew.bintray.com/bottles/git-lfs-2.12.0.mojave.bottle.tar.gz",
              "sha256": "a407e33c74000f21d71a3b4afdf874404e94c8f282eac7529e81a2da6ff29989"
            },
            "high_sierra": {
              "url": "https://homebrew.bintray.com/bottles/git-lfs-2.12.0.high_sierra.bottle.tar.gz",
              "sha256": "c5b7a9e92dc8783a208bdafbd6d4c2337665b5f3e3379e6d1096b4c928029141"
            }
          }
        }
      },
      "git-sizer": {
        "version": "1.3.0",
        "bottle": {
          "cellar": ":any_skip_relocation",
          "prefix": "/usr/local",
          "files": {
            "catalina": {
              "url": "https://homebrew.bintray.com/bottles/git-sizer-1.3.0.catalina.bottle.tar.gz",
              "sha256": "5d465491e6d2fd3b025dd6ad8f1448ef6ee7dd18d84ef73e895cc483afb9b98c"
            },
            "mojave": {
              "url": "https://homebrew.bintray.com/bottles/git-sizer-1.3.0.mojave.bottle.tar.gz",
              "sha256": "4d4e1b47018c1b5efe0ae71996e1dad3f7b0ec4f9616793121463b1c092b03af"
            },
            "high_sierra": {
              "url": "https://homebrew.bintray.com/bottles/git-sizer-1.3.0.high_sierra.bottle.tar.gz",
              "sha256": "add468f96d564f1046a0908cc1f553c73a2ac672973f3c7a7bca47c12fd72867"
            },
            "sierra": {
              "url": "https://homebrew.bintray.com/bottles/git-sizer-1.3.0.sierra.bottle.tar.gz",
              "sha256": "b0a6d0757c623e8e6b1f2ed6e9fb05496b29dd6f615df72e615a7a6a8fb45e3e"
            }
          }
        }
      },
      "gnu-sed": {
        "version": "4.8",
        "bottle": {
          "cellar": ":any_skip_relocation",
          "prefix": "/usr/local",
          "files": {
            "catalina": {
              "url": "https://homebrew.bintray.com/bottles/gnu-sed-4.8.catalina.bottle.tar.gz",
              "sha256": "726be75d6d7155820b408a10e5c1a5ba1406374a7fc167af62524a4f4bbbc099"
            },
            "mojave": {
              "url": "https://homebrew.bintray.com/bottles/gnu-sed-4.8.mojave.bottle.tar.gz",
              "sha256": "093f16752e7dfb115c055f20aed090108b94edd47c40f5e50878d961359251b2"
            },
            "high_sierra": {
              "url": "https://homebrew.bintray.com/bottles/gnu-sed-4.8.high_sierra.bottle.tar.gz",
              "sha256": "865abe618c67037a4a419a05e0df2c6814fb3abdd6f631ea546aeba0aaf8eb78"
            }
          }
        }
      },
      "gnupg": {
        "version": "2.2.23",
        "bottle": {
          "cellar": "/usr/local/Cellar",
          "prefix": "/usr/local",
          "files": {
            "catalina": {
              "url": "https://homebrew.bintray.com/bottles/gnupg-2.2.23.catalina.bottle.tar.gz",
              "sha256": "f3d7b9b1b344cf3aa2108756d922d1b48214a46b569ae737c604b22f4001b640"
            },
            "mojave": {
              "url": "https://homebrew.bintray.com/bottles/gnupg-2.2.23.mojave.bottle.tar.gz",
              "sha256": "1587039c4678d1c500fe8a3ba6d25f8070828bbe2159fc9fd12cad534b09dd9a"
            },
            "high_sierra": {
              "url": "https://homebrew.bintray.com/bottles/gnupg-2.2.23.high_sierra.bottle.tar.gz",
              "sha256": "87b3d4b162e860382a2f5ab4ed468f324a389fca4cfddc5363e544f3ca370125"
            }
          }
        },
        "options": {
          "link": false
        }
      },
      "go": {
        "version": "1.15.2",
        "bottle": {
          "cellar": "/usr/local/Cellar",
          "prefix": "/usr/local",
          "files": {
            "catalina": {
              "url": "https://homebrew.bintray.com/bottles/go-1.15.2.catalina.bottle.tar.gz",
              "sha256": "dc31fb80b6f6d7d8db13db55d2994fc77d37ffeffcd56c755fbc2674a038227c"
            },
            "mojave": {
              "url": "https://homebrew.bintray.com/bottles/go-1.15.2.mojave.bottle.tar.gz",
              "sha256": "a85ee24aaee867a45aff503a0f70da50310390374f1a2e9cf793834f9ca474e6"
            },
            "high_sierra": {
              "url": "https://homebrew.bintray.com/bottles/go-1.15.2.high_sierra.bottle.tar.gz",
              "sha256": "abc48dd817025641accdcfac9c018db8f95d4bbeb347e4ca006a48d97f6ad82d"
            }
          }
        }
      },
      "graphviz": {
        "version": "2.44.1",
        "bottle": {
          "cellar": "/usr/local/Cellar",
          "prefix": "/usr/local",
          "files": {
            "catalina": {
              "url": "https://homebrew.bintray.com/bottles/graphviz-2.44.1.catalina.bottle.tar.gz",
              "sha256": "e1cc69e09c92ac1507e461e374de9a0b2d7b01d15e29bf43808f8f458303c67f"
            },
            "mojave": {
              "url": "https://homebrew.bintray.com/bottles/graphviz-2.44.1.mojave.bottle.tar.gz",
              "sha256": "facbce9f3c97e2ad4b0ebf7344da4937722d6ae03c2091853c0bdd4f0e313e08"
            },
            "high_sierra": {
              "url": "https://homebrew.bintray.com/bottles/graphviz-2.44.1.high_sierra.bottle.tar.gz",
              "sha256": "86d0bb5111d0f97f4de3b1542280815f0b11cfda64bdbea09ba6ea2764205b8a"
            }
          }
        }
      },
      "grep": {
        "version": "3.5",
        "bottle": {
          "cellar": ":any",
          "prefix": "/usr/local",
          "files": {
            "catalina": {
              "url": "https://homebrew.bintray.com/bottles/grep-3.5.catalina.bottle.tar.gz",
              "sha256": "9d3347c001171d788a12d0113de23d347722a0587ae27540aa01afb32d95aa3a"
            },
            "mojave": {
              "url": "https://homebrew.bintray.com/bottles/grep-3.5.mojave.bottle.tar.gz",
              "sha256": "6c8b53ccc62d1dc82c07f4758909d74be944f2f2770fd3a147660a70a78b95e7"
            },
            "high_sierra": {
              "url": "https://homebrew.bintray.com/bottles/grep-3.5.high_sierra.bottle.tar.gz",
              "sha256": "62f85b85c25c50ac0899a16fc83945f4361db6e4c8beae0e44d4a9f748291622"
            }
          }
        }
      },
      "httpie": {
        "version": "2.2.0_1",
        "bottle": {
          "cellar": ":any_skip_relocation",
          "prefix": "/usr/local",
          "files": {
            "catalina": {
              "url": "https://homebrew.bintray.com/bottles/httpie-2.2.0_1.catalina.bottle.tar.gz",
              "sha256": "6956f918eabb4070d81f28f26d995056246179276d322d1929610f89733740f0"
            },
            "mojave": {
              "url": "https://homebrew.bintray.com/bottles/httpie-2.2.0_1.mojave.bottle.tar.gz",
              "sha256": "772cd022ca55198ac20e90b510bbcd3e6d9adbeff81b6bf17d5063c1c2454b6c"
            },
            "high_sierra": {
              "url": "https://homebrew.bintray.com/bottles/httpie-2.2.0_1.high_sierra.bottle.tar.gz",
              "sha256": "f792c4ee6183335d70e3c57d28326df0479e9de55b2ab0696d50aac051183b02"
            }
          }
        }
      },
      "hub": {
        "version": "2.14.2",
        "bottle": {
          "cellar": ":any_skip_relocation",
          "prefix": "/usr/local",
          "files": {
            "catalina": {
              "url": "https://homebrew.bintray.com/bottles/hub-2.14.2.catalina.bottle.tar.gz",
              "sha256": "fdf05855839a9d7ec6e7bee6796e3cb5fc473500cffc002366cf98c09a805b69"
            },
            "mojave": {
              "url": "https://homebrew.bintray.com/bottles/hub-2.14.2.mojave.bottle.tar.gz",
              "sha256": "bcbae9c683d76f3395665467ba0f0c00c60c12c84022f72faba4b8981724b563"
            },
            "high_sierra": {
              "url": "https://homebrew.bintray.com/bottles/hub-2.14.2.high_sierra.bottle.tar.gz",
              "sha256": "8800cda4532784bf764ea6116a06c81d8d90bb3d36d8ecf295e64f9dd647c4ad"
            }
          }
        }
      },
      "jq": {
        "version": "1.6",
        "bottle": {
          "cellar": ":any",
          "prefix": "/usr/local",
          "files": {
            "catalina": {
              "url": "https://homebrew.bintray.com/bottles/jq-1.6.catalina.bottle.1.tar.gz",
              "sha256": "820a3c85fcbb63088b160c7edf125d7e55fc2c5c1d51569304499c9cc4b89ce8"
            },
            "mojave": {
              "url": "https://homebrew.bintray.com/bottles/jq-1.6.mojave.bottle.1.tar.gz",
              "sha256": "71f0e76c5b22e5088426c971d5e795fe67abee7af6c2c4ae0cf4c0eb98ed21ff"
            },
            "high_sierra": {
              "url": "https://homebrew.bintray.com/bottles/jq-1.6.high_sierra.bottle.1.tar.gz",
              "sha256": "dffcffa4ea13e8f0f2b45c5121e529077e135ae9a47254c32182231662ee9b72"
            },
            "sierra": {
              "url": "https://homebrew.bintray.com/bottles/jq-1.6.sierra.bottle.1.tar.gz",
              "sha256": "bb4d19dc026c2d72c53eed78eaa0ab982e9fcad2cd2acc6d13e7a12ff658e877"
            }
          }
        }
      },
      "libdvdcss": {
        "version": "1.4.2",
        "bottle": {
          "cellar": ":any",
          "prefix": "/usr/local",
          "files": {
            "catalina": {
              "url": "https://homebrew.bintray.com/bottles/libdvdcss-1.4.2.catalina.bottle.tar.gz",
              "sha256": "352a2c343c04e65ee38fe154c797a29cc9cca509212e2296e9cd54e3e824ce29"
            },
            "mojave": {
              "url": "https://homebrew.bintray.com/bottles/libdvdcss-1.4.2.mojave.bottle.tar.gz",
              "sha256": "645422cdd6facba8137146fd12df0538b27432a72bc79c5ca8c2667ab9fc70bc"
            },
            "high_sierra": {
              "url": "https://homebrew.bintray.com/bottles/libdvdcss-1.4.2.high_sierra.bottle.tar.gz",
              "sha256": "4029db91ed7536435bd29db6b67f55509be13e70b6170337edec72daad8992c4"
            },
            "sierra": {
              "url": "https://homebrew.bintray.com/bottles/libdvdcss-1.4.2.sierra.bottle.tar.gz",
              "sha256": "907d51957c4674ddeb27b458dcf5f1f4b382219bda893fc8908147acc1c2b1ea"
            },
            "el_capitan": {
              "url": "https://homebrew.bintray.com/bottles/libdvdcss-1.4.2.el_capitan.bottle.tar.gz",
              "sha256": "0aaed21ecd3c8d3b4a9997300a599de5a541689ab200a6ffce52167b2ce5b664"
            }
          }
        }
      },
      "libxml2": {
        "version": "2.9.10_1",
        "bottle": {
          "cellar": ":any",
          "prefix": "/usr/local",
          "files": {
            "catalina": {
              "url": "https://homebrew.bintray.com/bottles/libxml2-2.9.10_1.catalina.bottle.tar.gz",
              "sha256": "bab6280370d9e7171d34e79ed1c1caa9b0b772ef7a1568f448a654255a505d5e"
            },
            "mojave": {
              "url": "https://homebrew.bintray.com/bottles/libxml2-2.9.10_1.mojave.bottle.tar.gz",
              "sha256": "7185d4c64a25e546eaf525134210bfb21edffb0bfa93c122e4696ab3788cfbf3"
            },
            "high_sierra": {
              "url": "https://homebrew.bintray.com/bottles/libxml2-2.9.10_1.high_sierra.bottle.tar.gz",
              "sha256": "bff3e730b9531c1b5088d49633a740eb27938961dc762b7de344e06d85ea20ee"
            }
          }
        }
      },
      "lolcat": {
        "version": "100.0.1",
        "bottle": {
          "cellar": ":any_skip_relocation",
          "prefix": "/usr/local",
          "files": {
            "catalina": {
              "url": "https://homebrew.bintray.com/bottles/lolcat-100.0.1.catalina.bottle.tar.gz",
              "sha256": "c0e179d579938e4301f04b4896bb2c234f4b643e53e53cbd4a7f796978d2ea6d"
            },
            "mojave": {
              "url": "https://homebrew.bintray.com/bottles/lolcat-100.0.1.mojave.bottle.tar.gz",
              "sha256": "ac56190c6ec7e25d49f979aff7f6cc3e45820002ef22fbc444196b64de2590f9"
            },
            "high_sierra": {
              "url": "https://homebrew.bintray.com/bottles/lolcat-100.0.1.high_sierra.bottle.tar.gz",
              "sha256": "1eb5cf4cd5565e07659f37e2531be1e72b0e2e8e57587af229e230fa00315ed3"
            }
          }
        }
      },
      "mas": {
        "version": "1.7.1",
        "bottle": {
          "cellar": ":any",
          "prefix": "/usr/local",
          "files": {
            "catalina": {
              "url": "https://homebrew.bintray.com/bottles/mas-1.7.1.catalina.bottle.tar.gz",
              "sha256": "e6de2f98ebd21885a9827664fe1b7eea5516a7fd75d5b7383e3a9b088591a27f"
            },
            "mojave": {
              "url": "https://homebrew.bintray.com/bottles/mas-1.7.1.mojave.bottle.tar.gz",
              "sha256": "8b6dc4e261ebdc8e2f93afe87da3db4d482eb3d8a0358ab19a0485d434550e77"
            }
          }
        }
      },
      "mercurial": {
        "version": "5.5.2",
        "bottle": {
          "cellar": "/usr/local/Cellar",
          "prefix": "/usr/local",
          "files": {
            "catalina": {
              "url": "https://homebrew.bintray.com/bottles/mercurial-5.5.2.catalina.bottle.tar.gz",
              "sha256": "4e825ea14b93467d22bfc45e3e7664b2d722fa7f9173711acca61650c3dbd8c5"
            },
            "mojave": {
              "url": "https://homebrew.bintray.com/bottles/mercurial-5.5.2.mojave.bottle.tar.gz",
              "sha256": "9077db79a19701298455a005c04228ff8a111ffeb7f9becee8b4f368526f710c"
            },
            "high_sierra": {
              "url": "https://homebrew.bintray.com/bottles/mercurial-5.5.2.high_sierra.bottle.tar.gz",
              "sha256": "98885b56a85023d257f2362908712c1770cf0a779b1db8c3de3b3a06de652b83"
            }
          }
        }
      },
      "moreutils": {
        "version": "0.64",
        "bottle": {
          "cellar": ":any_skip_relocation",
          "prefix": "/usr/local",
          "files": {
            "catalina": {
              "url": "https://homebrew.bintray.com/bottles/moreutils-0.64.catalina.bottle.tar.gz",
              "sha256": "2acce86bfb602b3da4577cf429080a138b7a2e587e394b175889c4d190ef3bae"
            },
            "mojave": {
              "url": "https://homebrew.bintray.com/bottles/moreutils-0.64.mojave.bottle.tar.gz",
              "sha256": "e4d2496b670b5f4c8fcac0baaaa41afeced3b04ac962ce4963752cc233d68273"
            },
            "high_sierra": {
              "url": "https://homebrew.bintray.com/bottles/moreutils-0.64.high_sierra.bottle.tar.gz",
              "sha256": "80057e9363725a85da1200dfe87fe669a5dab3980375ad83330ce4b61cbac13c"
            }
          }
        }
      },
      "mosh": {
        "version": "1.3.2_12",
        "bottle": {
          "cellar": ":any",
          "prefix": "/usr/local",
          "files": {
            "catalina": {
              "url": "https://homebrew.bintray.com/bottles/mosh-1.3.2_12.catalina.bottle.tar.gz",
              "sha256": "80aa0652a09eacf7e786012d1db2382d7423d476b44c536c1a7a3312b4a5e45a"
            },
            "mojave": {
              "url": "https://homebrew.bintray.com/bottles/mosh-1.3.2_12.mojave.bottle.tar.gz",
              "sha256": "6d1567ab1ff2159a5bd346ed8b51bca5fd82506279b930bb10079dc1ea79f860"
            },
            "high_sierra": {
              "url": "https://homebrew.bintray.com/bottles/mosh-1.3.2_12.high_sierra.bottle.tar.gz",
              "sha256": "e82a65883dc605e100b159ccd55ffee43c14eb65086a02b8cceba67f1b524066"
            }
          }
        }
      },
      "nmap": {
        "version": "7.91",
        "bottle": {
          "cellar": "/usr/local/Cellar",
          "prefix": "/usr/local",
          "files": {
            "catalina": {
              "url": "https://homebrew.bintray.com/bottles/nmap-7.91.catalina.bottle.tar.gz",
              "sha256": "5592fb8c2fe633a6339ee61901122c075a4b44c002e2887bddfb2c4b3aa2885f"
            },
            "mojave": {
              "url": "https://homebrew.bintray.com/bottles/nmap-7.91.mojave.bottle.tar.gz",
              "sha256": "ba808d31033d996488fdf56664de1cf424fc942db794ab7030d40a1caad93aa8"
            },
            "high_sierra": {
              "url": "https://homebrew.bintray.com/bottles/nmap-7.91.high_sierra.bottle.tar.gz",
              "sha256": "b9a5b9d54fb0af76b1ce343e94f142b3421309fbeb81078d73e41bc2a9d862ea"
            }
          }
        }
      },
      "p7zip": {
        "version": "16.02_2",
        "bottle": {
          "cellar": ":any_skip_relocation",
          "prefix": "/usr/local",
          "files": {
            "catalina": {
              "url": "https://homebrew.bintray.com/bottles/p7zip-16.02_2.catalina.bottle.tar.gz",
              "sha256": "b9f5fb1321ce5738d0129b3c48f51fc36a947bd84450f95ce9caa90e767fbd1b"
            },
            "mojave": {
              "url": "https://homebrew.bintray.com/bottles/p7zip-16.02_2.mojave.bottle.tar.gz",
              "sha256": "0de20c4bd05dc5652ca5f188895bf74e52eb701aaed502a0d1271eb58236f898"
            },
            "high_sierra": {
              "url": "https://homebrew.bintray.com/bottles/p7zip-16.02_2.high_sierra.bottle.tar.gz",
              "sha256": "5951a42bd864da7dba5ef5781a2efba206daba8b6f75c60c0cfd910dae218482"
            },
            "sierra": {
              "url": "https://homebrew.bintray.com/bottles/p7zip-16.02_2.sierra.bottle.tar.gz",
              "sha256": "73fe6276e906f67cd28adc0f5a22c914d57fd3cfdd54134ad64e5330f710235a"
            }
          }
        }
      },
      "pandoc": {
        "version": "2.10.1",
        "bottle": {
          "cellar": ":any_skip_relocation",
          "prefix": "/usr/local",
          "files": {
            "catalina": {
              "url": "https://homebrew.bintray.com/bottles/pandoc-2.10.1.catalina.bottle.1.tar.gz",
              "sha256": "720d055d2bdafbe818f50e186e710f7a8178719b56cfafa1d1948af16df7d7ea"
            },
            "mojave": {
              "url": "https://homebrew.bintray.com/bottles/pandoc-2.10.1.mojave.bottle.1.tar.gz",
              "sha256": "7174b62811cd4d4116bcb5edcfb55793f733e39ad79d8e8914a8b5e2c71f2b78"
            },
            "high_sierra": {
              "url": "https://homebrew.bintray.com/bottles/pandoc-2.10.1.high_sierra.bottle.1.tar.gz",
              "sha256": "ef823fe9876a5a6c3fe25db6b8dbca7b372320f7e6f5c5b224a7696acf5c397b"
            }
          }
        }
      },
      "socat": {
        "version": "1.7.3.4",
        "bottle": {
          "cellar": ":any",
          "prefix": "/usr/local",
          "files": {
            "catalina": {
              "url": "https://homebrew.bintray.com/bottles/socat-1.7.3.4.catalina.bottle.tar.gz",
              "sha256": "78e28a89b73b096849654b737ea66b730738cb24f8217c25acd71ba3cb75a70c"
            },
            "mojave": {
              "url": "https://homebrew.bintray.com/bottles/socat-1.7.3.4.mojave.bottle.tar.gz",
              "sha256": "5f057eb82e1700ae32da92d5c114fabd6238cba21503f5eaf7190b56aaa35ded"
            },
            "high_sierra": {
              "url": "https://homebrew.bintray.com/bottles/socat-1.7.3.4.high_sierra.bottle.tar.gz",
              "sha256": "90ee610e6e72158e5e2322ae198f48025f80b351b89029621fdf4b9861391ddb"
            }
          }
        }
      },
      "ssh-copy-id": {
        "version": "8.3p1",
        "bottle": false
      },
      "tmux": {
        "version": "3.1b",
        "bottle": {
          "cellar": ":any",
          "prefix": "/usr/local",
          "files": {
            "catalina": {
              "url": "https://homebrew.bintray.com/bottles/tmux-3.1b.catalina.bottle.1.tar.gz",
              "sha256": "785c1b2e2518478621eb5ac894b3f0ed06d8fdc4d223dd476451ab26974e3803"
            },
            "mojave": {
              "url": "https://homebrew.bintray.com/bottles/tmux-3.1b.mojave.bottle.1.tar.gz",
              "sha256": "a8fb2df02c2e094404b6c56e2b9d15a35abd012913771ad311e08cc3572f0e4b"
            },
            "high_sierra": {
              "url": "https://homebrew.bintray.com/bottles/tmux-3.1b.high_sierra.bottle.1.tar.gz",
              "sha256": "5d43e03fc71740ec38c98b309adb2b6d198a20fcb14f76bc163232fda61fac23"
            }
          }
        }
      },
      "tree": {
        "version": "1.8.0",
        "bottle": {
          "cellar": ":any_skip_relocation",
          "prefix": "/usr/local",
          "files": {
            "catalina": {
              "url": "https://homebrew.bintray.com/bottles/tree-1.8.0.catalina.bottle.tar.gz",
              "sha256": "18f7984bdbab22251e9fc3c7832dbace5c7f7a77e8d63717bb0078385e2bf255"
            },
            "mojave": {
              "url": "https://homebrew.bintray.com/bottles/tree-1.8.0.mojave.bottle.tar.gz",
              "sha256": "7152288c457dd893de50fa9d6ac9a8599748564e1b3586eec8eff7057089051a"
            },
            "high_sierra": {
              "url": "https://homebrew.bintray.com/bottles/tree-1.8.0.high_sierra.bottle.tar.gz",
              "sha256": "107d965994381d34e90b58a62f1c306c1b8a698db2696cdd905ba65c801ecc3b"
            },
            "sierra": {
              "url": "https://homebrew.bintray.com/bottles/tree-1.8.0.sierra.bottle.tar.gz",
              "sha256": "07d980571469a0cc699c69a8726eee338f782ba61c041e58f01ddb2924d08aeb"
            }
          }
        }
      },
      "unrar": {
        "version": "5.9.4",
        "bottle": {
          "cellar": ":any",
          "prefix": "/usr/local",
          "files": {
            "catalina": {
              "url": "https://homebrew.bintray.com/bottles/unrar-5.9.4.catalina.bottle.tar.gz",
              "sha256": "90e0f209046471dda292a622ded80ed410e237cb7fc8e1d2653f0d57c470fc6b"
            },
            "mojave": {
              "url": "https://homebrew.bintray.com/bottles/unrar-5.9.4.mojave.bottle.tar.gz",
              "sha256": "a45568c9d67db8866971aec111e9e6d9d606549099f60240f2cf7c7096680270"
            },
            "high_sierra": {
              "url": "https://homebrew.bintray.com/bottles/unrar-5.9.4.high_sierra.bottle.tar.gz",
              "sha256": "ca9a590d0bce2de6e35ce02fdc7a6bb2d32265a945949e278fb7ae4c8d3c2dca"
            }
          }
        }
      },
      "vim": {
        "version": "8.2.1850",
        "bottle": {
          "cellar": "/usr/local/Cellar",
          "prefix": "/usr/local",
          "files": {
            "catalina": {
              "url": "https://homebrew.bintray.com/bottles/vim-8.2.1850.catalina.bottle.tar.gz",
              "sha256": "536a5140137041b7eaecbe0cafbe953af59b632a6417161699f6e2a10db3dc19"
            },
            "mojave": {
              "url": "https://homebrew.bintray.com/bottles/vim-8.2.1850.mojave.bottle.tar.gz",
              "sha256": "d4a93a8f0b74afe43d83f8917cec9bd3ac60f1598b3a8f3ad8a7b41847bebf33"
            },
            "high_sierra": {
              "url": "https://homebrew.bintray.com/bottles/vim-8.2.1850.high_sierra.bottle.tar.gz",
              "sha256": "4636072fb97fed3ace8134f110155bdc4aa95344d74293ee785d9893f3b71dca"
            }
          }
        }
      },
      "watch": {
        "version": "3.3.16",
        "bottle": {
          "cellar": ":any",
          "prefix": "/usr/local",
          "files": {
            "catalina": {
              "url": "https://homebrew.bintray.com/bottles/watch-3.3.16.catalina.bottle.tar.gz",
              "sha256": "011e48363fe62c7a4ba0dec746d5964ee25545bde7855a31db0cb411420df190"
            },
            "mojave": {
              "url": "https://homebrew.bintray.com/bottles/watch-3.3.16.mojave.bottle.tar.gz",
              "sha256": "d17aba6f80c530e6b91b30e088df60aab3dc84b2f57ca7499928322438b9f0d2"
            },
            "high_sierra": {
              "url": "https://homebrew.bintray.com/bottles/watch-3.3.16.high_sierra.bottle.tar.gz",
              "sha256": "13d63ebc419965182d98f10b25cc99961679e1ba5ce6118e66b7037eb4e78de8"
            }
          }
        }
      },
      "wget": {
        "version": "1.20.3_2",
        "bottle": {
          "cellar": "/usr/local/Cellar",
          "prefix": "/usr/local",
          "files": {
            "catalina": {
              "url": "https://homebrew.bintray.com/bottles/wget-1.20.3_2.catalina.bottle.tar.gz",
              "sha256": "ef65c759c5097a36323fa9c77756468649e8d1980a3a4e05695c05e39568967c"
            },
            "mojave": {
              "url": "https://homebrew.bintray.com/bottles/wget-1.20.3_2.mojave.bottle.tar.gz",
              "sha256": "28f4090610946a4eb207df102d841de23ced0d06ba31cb79e040d883906dcd4f"
            },
            "high_sierra": {
              "url": "https://homebrew.bintray.com/bottles/wget-1.20.3_2.high_sierra.bottle.tar.gz",
              "sha256": "91dd0caca9bd3f38c439d5a7b6f68440c4274945615fae035ff0a369264b8a2f"
            }
          }
        }
      },
      "wimlib": {
        "version": "1.13.2",
        "bottle": {
          "cellar": ":any",
          "prefix": "/usr/local",
          "files": {
            "catalina": {
              "url": "https://homebrew.bintray.com/bottles/wimlib-1.13.2.catalina.bottle.tar.gz",
              "sha256": "9b1f59782b773025346f9e466926467035c3e007f54acc77caa332b73a9308bf"
            },
            "mojave": {
              "url": "https://homebrew.bintray.com/bottles/wimlib-1.13.2.mojave.bottle.tar.gz",
              "sha256": "9c516e253677057ba243d2d0c30894df407c5d24a23d055d8b7152f6f3267991"
            },
            "high_sierra": {
              "url": "https://homebrew.bintray.com/bottles/wimlib-1.13.2.high_sierra.bottle.tar.gz",
              "sha256": "543e598241edae31ae469dd6da5ceaf10f1ef658ea051e1be0d5241393d167b6"
            }
          }
        }
      },
      "zsh": {
        "version": "5.8",
        "bottle": {
          "cellar": "/usr/local/Cellar",
          "prefix": "/usr/local",
          "files": {
            "catalina": {
              "url": "https://homebrew.bintray.com/bottles/zsh-5.8.catalina.bottle.tar.gz",
              "sha256": "209d04a4d62f6162f1b6cf824d2c50b00b52cb812c04c1967e5b376573b5aef0"
            },
            "mojave": {
              "url": "https://homebrew.bintray.com/bottles/zsh-5.8.mojave.bottle.tar.gz",
              "sha256": "c5c35657637c97132efbaa0fd8e2add568aaa62adfe66e7d19f961f8e9506da9"
            },
            "high_sierra": {
              "url": "https://homebrew.bintray.com/bottles/zsh-5.8.high_sierra.bottle.tar.gz",
              "sha256": "029b8c6922f01bfd832dd0f4f940f99328d2495714c37c1dc7ef326d6fb1459e"
            }
          }
        }
      },
      "zsh-completions": {
        "version": "0.32.0",
        "bottle": false
      },
      "github/gh/gh": null,
      "shellcheck": {
        "version": "0.7.1",
        "bottle": {
          "cellar": ":any_skip_relocation",
          "prefix": "/usr/local",
          "files": {
            "catalina": {
              "url": "https://homebrew.bintray.com/bottles/shellcheck-0.7.1.catalina.bottle.1.tar.gz",
              "sha256": "0cd635d2172d5e6617be8cdfb2723b6aa6feb2aa22e36cb3172d8b6fa012f4a0"
            },
            "mojave": {
              "url": "https://homebrew.bintray.com/bottles/shellcheck-0.7.1.mojave.bottle.1.tar.gz",
              "sha256": "37201a49c0d7a5be49c5d97d4f6f8f5fcfef7d700b4694f74648a1addcd6783d"
            },
            "high_sierra": {
              "url": "https://homebrew.bintray.com/bottles/shellcheck-0.7.1.high_sierra.bottle.1.tar.gz",
              "sha256": "1b20aeaba4d5e2e3df5cbe27636d655b6f877ee05a41d25fe1e0b3f9d00afa81"
            }
          }
        }
      },
      "shfmt": {
        "version": "3.1.2",
        "bottle": {
          "cellar": ":any_skip_relocation",
          "prefix": "/usr/local",
          "files": {
            "catalina": {
              "url": "https://homebrew.bintray.com/bottles/shfmt-3.1.2.catalina.bottle.tar.gz",
              "sha256": "42bd98e64ae352448f09fdc2b56a71e36e3659e382338447e94d20f4d7befcff"
            },
            "mojave": {
              "url": "https://homebrew.bintray.com/bottles/shfmt-3.1.2.mojave.bottle.tar.gz",
              "sha256": "d58c28c678be4be515c4a22e99338f7b1120a9f9d2eb004b6d7863a284ad5295"
            },
            "high_sierra": {
              "url": "https://homebrew.bintray.com/bottles/shfmt-3.1.2.high_sierra.bottle.tar.gz",
              "sha256": "127c0adf737c2de8d0a23850249b7cbc22fe5f864434c331ed521d4f00f3f3f7"
            }
          }
        }
      },
      "yq": {
        "version": "3.4.0",
        "bottle": {
          "cellar": ":any_skip_relocation",
          "prefix": "/usr/local",
          "files": {
            "catalina": {
              "url": "https://homebrew.bintray.com/bottles/yq-3.4.0.catalina.bottle.tar.gz",
              "sha256": "a4679c723a46faa9921951239e5ec7d97570c42e521eefd772c2dcb6999187b9"
            },
            "mojave": {
              "url": "https://homebrew.bintray.com/bottles/yq-3.4.0.mojave.bottle.tar.gz",
              "sha256": "c5d57a09d20dac8753fd41f1738e80594684e6a714d210483ba9f8d687ad0344"
            },
            "high_sierra": {
              "url": "https://homebrew.bintray.com/bottles/yq-3.4.0.high_sierra.bottle.tar.gz",
              "sha256": "b88ba305a70f8054611de1bdab8954c9864b456374e70d499bc1241895e3ee4d"
            }
          }
        }
      },
      "openssl@1.1": {
        "version": "1.1.1h",
        "bottle": {
          "cellar": "/usr/local/Cellar",
          "prefix": "/usr/local",
          "files": {
            "catalina": {
              "url": "https://homebrew.bintray.com/bottles/openssl%401.1-1.1.1h.catalina.bottle.tar.gz",
              "sha256": "4e5357c0cfd55cfa4ef0b632c6fc9f49d39337dd070dc12d3c862e28bd28f079"
            },
            "mojave": {
              "url": "https://homebrew.bintray.com/bottles/openssl%401.1-1.1.1h.mojave.bottle.tar.gz",
              "sha256": "d4ef27b41d0596d20b79a43a43554d4ea1395f0ef9affdcf0ce74114a00e2572"
            },
            "high_sierra": {
              "url": "https://homebrew.bintray.com/bottles/openssl%401.1-1.1.1h.high_sierra.bottle.tar.gz",
              "sha256": "face6b0b99e7d628232e379f02aeb9d0eb7d1b5efba77561e0fd9edba130393d"
            }
          }
        }
      },
      "qrcp": {
        "version": "0.7.0",
        "bottle": {
          "cellar": ":any_skip_relocation",
          "prefix": "/usr/local",
          "files": {
            "catalina": {
              "url": "https://homebrew.bintray.com/bottles/qrcp-0.7.0.catalina.bottle.tar.gz",
              "sha256": "206c26baa2c75ed1eb52a511db3c1010cdd9278ef9766c972e58f80eca317ec7"
            },
            "mojave": {
              "url": "https://homebrew.bintray.com/bottles/qrcp-0.7.0.mojave.bottle.tar.gz",
              "sha256": "b1649f24a58cda7ff00033713123b198fced346dc136ad215f5c54cf4dfd8e20"
            },
            "high_sierra": {
              "url": "https://homebrew.bintray.com/bottles/qrcp-0.7.0.high_sierra.bottle.tar.gz",
              "sha256": "8edff5868b49d3e96be74dbfd2287c95a7721963fc8b06410a4c903da7e16167"
            }
          }
        }
      },
      "svn": null
    },
    "cask": {
      "1password": {
        "version": "7.6",
        "options": {
          "full_name": "1password"
        }
      },
      "atom": {
        "version": "1.52.0",
        "options": {
          "full_name": "atom"
        }
      },
      "avidemux": {
        "version": "2.7.6",
        "options": {
          "full_name": "avidemux"
        }
      },
      "balenaetcher": {
        "version": "1.5.95",
        "options": {
          "full_name": "balenaetcher"
        }
      },
      "boxer": {
        "version": "1.4.0",
        "options": {
          "full_name": "boxer"
        }
      },
      "docker": {
        "version": "2.3.0.3,45519",
        "options": {
          "full_name": "docker"
        }
      },
      "dropbox": {
        "version": "latest",
        "options": {
          "full_name": "dropbox"
        }
      },
      "encryptme": {
        "version": "4.2.1",
        "options": {
          "full_name": "encryptme"
        }
      },
      "epic-games": {
        "version": "7.16.0",
        "options": {
          "full_name": "epic-games"
        }
      },
      "firefox": {
        "version": "81.0.2",
        "options": {
          "full_name": "firefox"
        }
      },
      "font-anonymice-powerline": {
        "version": "latest",
        "options": {
          "full_name": "font-anonymice-powerline"
        }
      },
      "font-consolas-for-powerline": {
        "version": "latest",
        "options": {
          "full_name": "font-consolas-for-powerline"
        }
      },
      "font-dejavu-sans-mono-for-powerline": {
        "version": "latest",
        "options": {
          "full_name": "font-dejavu-sans-mono-for-powerline"
        }
      },
      "font-droid-sans-mono-for-powerline": {
        "version": "latest",
        "options": {
          "full_name": "font-droid-sans-mono-for-powerline"
        }
      },
      "font-fira-mono-for-powerline": {
        "version": "latest",
        "options": {
          "full_name": "font-fira-mono-for-powerline"
        }
      },
      "font-inconsolata-dz-for-powerline": {
        "version": "latest",
        "options": {
          "full_name": "font-inconsolata-dz-for-powerline"
        }
      },
      "font-inconsolata-for-powerline": {
        "version": "latest",
        "options": {
          "full_name": "font-inconsolata-for-powerline"
        }
      },
      "font-inconsolata-for-powerline-bold": {
        "version": "latest",
        "options": {
          "full_name": "font-inconsolata-for-powerline-bold"
        }
      },
      "font-inconsolata-g-for-powerline": {
        "version": "latest",
        "options": {
          "full_name": "font-inconsolata-g-for-powerline"
        }
      },
      "font-jetbrains-mono": {
        "version": "2.002",
        "options": {
          "full_name": "font-jetbrains-mono"
        }
      },
      "font-liberation-mono-for-powerline": {
        "version": "latest",
        "options": {
          "full_name": "font-liberation-mono-for-powerline"
        }
      },
      "font-menlo-for-powerline": {
        "version": "latest",
        "options": {
          "full_name": "font-menlo-for-powerline"
        }
      },
      "font-meslo-for-powerline": {
        "version": "2015-12-04",
        "options": {
          "full_name": "font-meslo-for-powerline"
        }
      },
      "font-monofur-for-powerline": {
        "version": "latest",
        "options": {
          "full_name": "font-monofur-for-powerline"
        }
      },
      "font-noto-mono-for-powerline": {
        "version": "latest",
        "options": {
          "full_name": "font-noto-mono-for-powerline"
        }
      },
      "font-powerline-symbols": {
        "version": "latest",
        "options": {
          "full_name": "font-powerline-symbols"
        }
      },
      "font-roboto-mono-for-powerline": {
        "version": "latest",
        "options": {
          "full_name": "font-roboto-mono-for-powerline"
        }
      },
      "font-source-code-pro-for-powerline": {
        "version": "latest",
        "options": {
          "full_name": "font-source-code-pro-for-powerline"
        }
      },
      "font-ubuntu-mono-derivative-powerline": {
        "version": "latest",
        "options": {
          "full_name": "font-ubuntu-mono-derivative-powerline"
        }
      },
      "gog-galaxy": {
        "version": "1.2.44.30",
        "options": {
          "full_name": "gog-galaxy"
        }
      },
      "google-backup-and-sync": {
        "version": "latest",
        "options": {
          "full_name": "google-backup-and-sync"
        }
      },
      "gpg-suite": {
        "version": "2020.1",
        "options": {
          "full_name": "gpg-suite"
        }
      },
      "handbrake": {
        "version": "1.3.3",
        "options": {
          "full_name": "handbrake"
        }
      },
      "intellij-idea": {
        "version": "2020.1.1",
        "options": {
          "full_name": "intellij-idea"
        }
      },
      "iterm2": {
        "version": "3.3.12",
        "options": {
          "full_name": "iterm2"
        }
      },
      "kid3": {
        "version": "3.8.4",
        "options": {
          "full_name": "kid3"
        }
      },
      "lg-onscreen-control": {
        "version": "3.82,U6LpEY8y0TeDxWGmkuVxqw",
        "options": {
          "full_name": "lg-onscreen-control"
        }
      },
      "logitech-myharmony": {
        "version": "1.0.0.97",
        "options": {
          "full_name": "logitech-myharmony"
        }
      },
      "marked": {
        "version": "2.6.1,1007",
        "options": {
          "full_name": "marked"
        }
      },
      "microsoft-azure-storage-explorer": {
        "version": "latest",
        "options": {
          "full_name": "microsoft-azure-storage-explorer"
        }
      },
      "microsoft-teams": {
        "version": "1.3.00.9271",
        "options": {
          "full_name": "microsoft-teams"
        }
      },
      "nightowl": {
        "version": "0.2.9",
        "options": {
          "full_name": "nightowl"
        }
      },
      "openemu": {
        "version": "2.2.1",
        "options": {
          "full_name": "openemu"
        }
      },
      "pycharm-ce": {
        "version": "2020.1.1,201.7223.92",
        "options": {
          "full_name": "pycharm-ce"
        }
      },
      "razer-synapse": {
        "version": "1.87.1",
        "options": {
          "full_name": "razer-synapse"
        }
      },
      "selfcontrol": {
        "version": "3.0.3",
        "options": {
          "full_name": "selfcontrol"
        }
      },
      "slack": {
        "version": "4.10.3",
        "options": {
          "full_name": "slack"
        }
      },
      "sourcetree": {
        "version": "4.0.1_234",
        "options": {
          "full_name": "sourcetree"
        }
      },
      "steam": {
        "version": "latest",
        "options": {
          "full_name": "steam"
        }
      },
      "subler": {
        "version": "1.6.7",
        "options": {
          "full_name": "subler"
        }
      },
      "sublime-text": {
        "version": "3.211",
        "options": {
          "full_name": "sublime-text"
        }
      },
      "synology-drive": {
        "version": "2.0.2,11078",
        "options": {
          "full_name": "synology-drive"
        }
      },
      "vagrant": {
        "version": "2.2.9",
        "options": {
          "full_name": "vagrant"
        }
      },
      "viscosity": {
        "version": "1.7.11",
        "options": {
          "full_name": "viscosity"
        }
      },
      "visualvm": {
        "version": "2.0.2",
        "options": {
          "full_name": "visualvm"
        }
      },
      "vlc": {
        "version": "3.0.11.1",
        "options": {
          "full_name": "vlc"
        }
      },
      "xld": {
        "version": "2019.10.04",
        "options": {
          "full_name": "xld"
        }
      },
      "zoomus": {
        "version": "5.0.25694.0524",
        "options": {
          "full_name": "zoomus"
        }
      },
      "slowquitapps": {
        "version": "0.8.0",
        "options": {
          "full_name": "slowquitapps"
        }
      },
      "1password-cli": {
        "version": "1.7.0",
        "options": {
          "full_name": "1password-cli"
        }
      },
      "alfred": {
        "version": "4.1.1_1172",
        "options": {
          "full_name": "alfred"
        }
      },
      "browserosaurus": {
        "version": "12.3.1",
        "options": {
          "full_name": "browserosaurus"
        }
      },
      "finicky": {
        "version": "3.1.1",
        "options": {
          "full_name": "finicky"
        }
      },
      "font-kernit": {
        "version": "1.0.0",
        "options": {
          "full_name": "font-kernit"
        }
      },
      "logitech-camera-settings": {
        "version": "3.0.12",
        "options": {
          "full_name": "logitech-camera-settings"
        }
      }
    },
    "mas": {
      "Airmail": {
        "id": "918858936",
        "version": "4.1.6"
      },
      "Amphetamine": {
        "id": "937984704",
        "version": "5.0.3"
      },
      "Apple Configurator 2": {
        "id": "1037126344",
        "version": "2.13.1"
      },
      "Bridge Constructor Portal": {
        "id": "1316061122",
        "version": "5.0"
      },
      "GarageBand": {
        "id": "682658836",
        "version": "10.3.5"
      },
      "iMovie": {
        "id": "408981434",
        "version": "10.1.16"
      },
      "iPhoto": {
        "id": "408981381",
        "version": "9.6.1"
      },
      "Keynote": {
        "id": "409183694",
        "version": "10.2"
      },
      "Magnet": {
        "id": "441258766",
        "version": "2.4.8"
      },
      "NetSpot": {
        "id": "514951692",
        "version": "2.12.1016"
      },
      "Notability": {
        "id": "736189492",
        "version": "4.4.1"
      },
      "Numbers": {
        "id": "409203825",
        "version": "10.2"
      },
      "Pages": {
        "id": "409201541",
        "version": "10.2"
      },
      "Reeder": {
        "id": "1449412482",
        "version": "4.2.8"
      },
      "Server": {
        "id": "883878097",
        "version": "5.8"
      },
      "Paprika Recipe Manager 3": {
        "id": "1303222628",
        "version": "3.5.1"
      },
      "SmileAllDay": {
        "id": "1180442868",
        "version": "2.3.4"
      }
    }
  },
  "system": {
    "macos": {
      "mojave": {
        "HOMEBREW_VERSION": "2.3.0-16-g0305001",
        "HOMEBREW_PREFIX": "/usr/local",
        "Homebrew/homebrew-core": "fee8ef799946ad413b65161b57dca7abd9715452",
        "CLT": "10.3.0.0.1.1562985497",
        "Xcode": "10.3",
        "macOS": "10.14.6"
      },
      "catalina": {
        "HOMEBREW_VERSION": "2.5.6",
        "HOMEBREW_PREFIX": "/usr/local",
        "Homebrew/homebrew-core": "a5a91200d6813d2c14e6787b70707571e82485c8",
        "CLT": "12.0.0.0.1.1599194153",
        "Xcode": "12.0",
        "macOS": "10.15.7"
      }
    }
  }
}
